nuggetpackage/__init__.py
nuggetpackage/AJAX PROGRESS CONTROL AND TREE VIEW CONTROL EXAMPLE/ASPX1.txt
nuggetpackage/AJAX PROGRESS CONTROL AND TREE VIEW CONTROL EXAMPLE/ASPX2.txt
nuggetpackage/AJAX PROGRESS CONTROL AND TREE VIEW CONTROL EXAMPLE/CS1.txt
nuggetpackage/AJAX PROGRESS CONTROL AND TREE VIEW CONTROL EXAMPLE/CS2.txt
nuggetpackage/AJAX PROGRESS CONTROL AND TREE VIEW CONTROL EXAMPLE/SITEMAP2.txt
nuggetpackage/CONSOLE OPERATION AND CALENDOR CONTROL/ASPX.txt
nuggetpackage/CONSOLE OPERATION AND CALENDOR CONTROL/CONSOLE.txt
nuggetpackage/CONSOLE OPERATION AND CALENDOR CONTROL/CS.txt
nuggetpackage/DATE OPERATION AND STUDENT DETAILS SHOW USING GRIDVIEW/ASPX 2.txt
nuggetpackage/DATE OPERATION AND STUDENT DETAILS SHOW USING GRIDVIEW/ASPX.txt
nuggetpackage/DATE OPERATION AND STUDENT DETAILS SHOW USING GRIDVIEW/CS.txt
nuggetpackage/DATE OPERATION AND STUDENT DETAILS SHOW USING GRIDVIEW/CS2.txt
nuggetpackage/DATE OPERATION AND STUDENT DETAILS SHOW USING GRIDVIEW/DB.txt
nuggetpackage/FIBONESIS PRIME NUMBER AND DATA ACCESS DISCONNECTED USING GRIDVIEW/ASPX.txt
nuggetpackage/FIBONESIS PRIME NUMBER AND DATA ACCESS DISCONNECTED USING GRIDVIEW/CONSOLE.txt
nuggetpackage/FIBONESIS PRIME NUMBER AND DATA ACCESS DISCONNECTED USING GRIDVIEW/CS.txt
nuggetpackage/JS BUTTON AND ADD MULTI SUB DIV USING TEXTBOX/ASPX 2.txt
nuggetpackage/JS BUTTON AND ADD MULTI SUB DIV USING TEXTBOX/ASPX.txt
nuggetpackage/JS BUTTON AND ADD MULTI SUB DIV USING TEXTBOX/CS.txt
nuggetpackage/JS BUTTON AND ADD MULTI SUB DIV USING TEXTBOX/CS2.txt
nuggetpackage/MULTI INHERITENCE AND GRIDVIEW/ASPX.txt
nuggetpackage/MULTI INHERITENCE AND GRIDVIEW/CONSOLE.txt
nuggetpackage/MULTI INHERITENCE AND GRIDVIEW/CS.txt
nuggetpackage/MULTI INHERITENCE AND GRIDVIEW/DB.txt
nuggetpackage/SETTING AND USE OF SERVER CONTROL PROPERTIES AND COUNT/ASPX 2.txt
nuggetpackage/SETTING AND USE OF SERVER CONTROL PROPERTIES AND COUNT/ASPX.txt
nuggetpackage/SETTING AND USE OF SERVER CONTROL PROPERTIES AND COUNT/CS.txt
nuggetpackage-0.1.0.dist-info/LICENSE
nuggetpackage-0.1.0.dist-info/METADATA
nuggetpackage-0.1.0.dist-info/WHEEL
nuggetpackage-0.1.0.dist-info/top_level.txt
nuggetpackage-0.1.0.dist-info/RECORD
